setup.py
Scoot.egg-info/PKG-INFO
Scoot.egg-info/SOURCES.txt
Scoot.egg-info/dependency_links.txt
Scoot.egg-info/requires.txt
Scoot.egg-info/top_level.txt
scoot/__init__.py
scoot/client_lib.py
scoot/daemon_pb2.py