Metadata-Version: 1.0
Name: Scoot
Version: 0.3
Summary: Scoot library for connecting to a local Scoot Daemon Server
Home-page: https://github.com/scootdev/scoot
Author: UNKNOWN
Author-email: UNKNOWN
License: UNKNOWN
Platform: UNKNOWN
